airops/__init__.py
airops/config.py
airops/errors.py
airops/http.py
airops/outputs.py
airops/py.typed
airops/tool.py
airops/cli/__init__.py
airops/cli/init.py
airops/cli/publish.py
airops/cli/run.py
airops/cli/templates/__init__.py
airops/cli/templates/agents.md.jinja
airops/cli/templates/claude.md.jinja
airops/cli/templates/dockerfile.jinja
airops/cli/templates/dockerignore.jinja
airops/cli/templates/env_example.jinja
airops/cli/templates/pyproject.toml.jinja
airops/cli/templates/readme.md.jinja
airops/cli/templates/test_tool.py.jinja
airops/cli/templates/tool.py.jinja
airops/inputs/__init__.py
airops/inputs/metadata.py
airops/inputs/schema.py
airops/inputs/types.py
airops/publish/__init__.py
airops/publish/builder.py
airops/publish/client.py
airops/publish/loader.py
airops/secrets/__init__.py
airops/secrets/client.py
airops/server/__init__.py
airops/server/app.py
airops/server/routes.py
airops/server/store.py
airops/server/ui.py
airops/steps/__init__.py
airops/steps/client.py
airops-0.2.0.dist-info/METADATA
airops-0.2.0.dist-info/WHEEL
airops-0.2.0.dist-info/entry_points.txt
airops-0.2.0.dist-info/RECORD
