Metadata-Version: 2.4
Name: airops
Version: 0.2.0
Summary: AirOps Python SDK for building custom tools that integrate with AirOps Steps API
Project-URL: Homepage, https://airops.com
Project-URL: Documentation, https://docs.airops.com
Project-URL: Repository, https://github.com/airops/airops-sdk
Author-email: AirOps <support@airops.com>
License-Expression: MIT
Classifier: Development Status :: 3 - Alpha
Classifier: Intended Audience :: Developers
Classifier: License :: OSI Approved :: MIT License
Classifier: Programming Language :: Python :: 3
Classifier: Programming Language :: Python :: 3.13
Classifier: Topic :: Software Development :: Libraries :: Python Modules
Requires-Python: >=3.13
Requires-Dist: fastapi>=0.115.0
Requires-Dist: fastui>=0.7.0
Requires-Dist: httpx>=0.28.0
Requires-Dist: jinja2>=3.0.0
Requires-Dist: pydantic>=2.10.0
Requires-Dist: python-dotenv>=1.0.0
Requires-Dist: python-multipart>=0.0.9
Requires-Dist: rich>=13.0.0
Requires-Dist: tenacity>=9.0.0
Requires-Dist: uvicorn[standard]>=0.34.0
Provides-Extra: dev
Requires-Dist: mypy>=1.14.0; extra == 'dev'
Requires-Dist: pytest-asyncio>=0.24.0; extra == 'dev'
Requires-Dist: pytest-httpx>=0.35.0; extra == 'dev'
Requires-Dist: pytest>=8.0.0; extra == 'dev'
Requires-Dist: ruff>=0.8.0; extra == 'dev'
